poet/.DS_Store
poet/README.rst
poet/poet/__init__.py
poet/pyproject.toml
poet/tests/__init__.py
poet/tests/test_poet.py
crypto_project-0.1.0.dist-info/WHEEL
crypto_project-0.1.0.dist-info/METADATA
crypto_project-0.1.0.dist-info/RECORD
