Metadata-Version: 2.1
Name: crypto-project
Version: 0.1.0
Summary: Crypto production
License: @
Author: Melo & Deemz
Requires-Python: >=3.8,<4.0
Classifier: License :: Other/Proprietary License
Classifier: Programming Language :: Python :: 3
Classifier: Programming Language :: Python :: 3.8
Classifier: Programming Language :: Python :: 3.9
Requires-Dist: binance (>=0.3,<0.4)
Requires-Dist: coda (>=0.1.0,<0.2.0)
Requires-Dist: matplotlib (>=3.4.2,<4.0.0)
Requires-Dist: numpy (>=1.20.3,<2.0.0)
